README.md
setup.py
meituan/__init__.py
meituan/exceptions.py
meituan/pay.py
meituan/utils.py
meituan/api/__init__.py
meituan/api/base.py
meituan/api/micro.py
openmeituan.egg-info/PKG-INFO
openmeituan.egg-info/SOURCES.txt
openmeituan.egg-info/dependency_links.txt
openmeituan.egg-info/not-zip-safe
openmeituan.egg-info/requires.txt
openmeituan.egg-info/top_level.txt