Metadata-Version: 1.0
Name: openmeituan
Version: 0.1.1
Summary: an implementation of meituan open platform's APIs
Home-page: https://github.com/farseer810/openmeituan
Author: farseer810
Author-email: farseer810@qq.com
License: MIT
Keywords: meituan meituan pay library
Platform: UNKNOWN
